Metadata-Version: 1.1
Name: mk-instagram-api
Version: 0.0.0
Summary: Object-Oriented Instagram Private API
Home-page: https://github.com/MichaelKim0407/instagram-api
Author: Michael Kim
Author-email: mkim0407@gmail.com
License: MIT
Platform: UNKNOWN
Classifier: Development Status :: 1 - Planning
Classifier: Intended Audience :: Developers
Classifier: License :: OSI Approved :: MIT License
Classifier: Programming Language :: Python :: 3.6
Classifier: Topic :: Software Development :: Libraries
